robotstxtparser.py
tests/__init__.py
tests/test_robots.py
robots_txt_parser-1.0.1.dist-info/LICENSE
robots_txt_parser-1.0.1.dist-info/METADATA
robots_txt_parser-1.0.1.dist-info/WHEEL
robots_txt_parser-1.0.1.dist-info/top_level.txt
robots_txt_parser-1.0.1.dist-info/RECORD
